stak_git/__init__.py
stak_git/stak
stak_git-1.0.4.data/data/bin/stak
stak_git-1.0.4.dist-info/METADATA
stak_git-1.0.4.dist-info/WHEEL
stak_git-1.0.4.dist-info/entry_points.txt
stak_git-1.0.4.dist-info/licenses/LICENSE
stak_git-1.0.4.dist-info/RECORD
