Metadata-Version: 2.4
Name: stak-git
Version: 1.0.4
Summary: Minimal stacked changes for git - build big features as small branches
Project-URL: Homepage, https://github.com/memorypasta/stak
Project-URL: Repository, https://github.com/memorypasta/stak
Project-URL: Issues, https://github.com/memorypasta/stak/issues
Author-email: memorypasta <memorypasta@gmail.com>
License-Expression: MIT
License-File: LICENSE
Keywords: cli,code-review,git,stacked-branches,stacked-diffs,workflow
Classifier: Development Status :: 4 - Beta
Classifier: Environment :: Console
Classifier: Intended Audience :: Developers
Classifier: License :: OSI Approved :: MIT License
Classifier: Operating System :: MacOS
Classifier: Operating System :: POSIX :: Linux
Classifier: Programming Language :: Unix Shell
Classifier: Topic :: Software Development :: Version Control :: Git
Requires-Python: >=3.8
